ny_artsy_date/.DS_Store
ny_artsy_date/__init__.py
ny_artsy_date/ny_artsy_date.py
ny_artsy_date-0.1.0.dist-info/LICENSE
ny_artsy_date-0.1.0.dist-info/WHEEL
ny_artsy_date-0.1.0.dist-info/METADATA
ny_artsy_date-0.1.0.dist-info/RECORD
