Metadata-Version: 2.1
Name: ny-artsy-date
Version: 0.1.0
Summary: A Python package to provide easy access to current and upcoming art-based events within a walkable / bikeable distance (500-3000 meters) in the New York Metro area using NYC ArtBeats and Google Maps API's.
License: MIT
Author: Connie (Ye) Xu 
Requires-Python: >=3.9,<3.11
Classifier: License :: OSI Approved :: MIT License
Classifier: Programming Language :: Python :: 3
Classifier: Programming Language :: Python :: 3.9
Requires-Dist: gmaps (>=0.9.0,<0.10.0)
Requires-Dist: googlemaps (>=4.5.3,<5.0.0)
Requires-Dist: lxml (>=4.7.1,<5.0.0)
Requires-Dist: numpy (>=1.21.4,<2.0.0)
Requires-Dist: pandas (>=1.3.5,<2.0.0)
Requires-Dist: pytest (>=6.2.5,<7.0.0)
Requires-Dist: pytest-cov (>=3.0.0,<4.0.0)
Requires-Dist: requests (>=2.26.0,<3.0.0)
